gc9d01_library/GC9D01.py
gc9d01_library/__init__.py
gc9d01_library/displaytest.py
gc9d01_library/font5x7.py
gc9d01_library-0.1.4.dist-info/LICENSE
gc9d01_library-0.1.4.dist-info/METADATA
gc9d01_library-0.1.4.dist-info/WHEEL
gc9d01_library-0.1.4.dist-info/top_level.txt
gc9d01_library-0.1.4.dist-info/RECORD
