Metadata-Version: 2.1
Name: gc9d01_library
Version: 0.1.4
Summary: A Python driver for the GC9D01 round LCD display on Raspberry Pi
Home-page: https://github.com/Marc4t/gc9d01_library
Author: Marc D
Author-email: marcdanielt@gmail.com
Classifier: Development Status :: 3 - Alpha
Classifier: Intended Audience :: Developers
Classifier: Topic :: Software Development :: Libraries :: Python Modules
Classifier: License :: OSI Approved :: MIT License
Classifier: Programming Language :: Python :: 3
Classifier: Programming Language :: Python :: 3.7
Classifier: Programming Language :: Python :: 3.8
Classifier: Programming Language :: Python :: 3.9
Requires-Python: >=3.7
License-File: LICENSE
Requires-Dist: adafruit-blinka
Requires-Dist: adafruit-circuitpython-busdevice
